walytis_offchain/__init__.py
walytis_offchain/blockstore.py
walytis_offchain/data_block.py
walytis_offchain/log.py
walytis_offchain/private_blockchain.py
walytis_offchain/threaded_object.py
walytis_offchain-0.5.1.dist-info/licenses/LICENSE
walytis_offchain-0.5.1.dist-info/licenses/LICENSE-CC0
walytis_offchain-0.5.1.dist-info/METADATA
walytis_offchain-0.5.1.dist-info/WHEEL
walytis_offchain-0.5.1.dist-info/top_level.txt
walytis_offchain-0.5.1.dist-info/RECORD
