Metadata-Version: 2.4
Name: walytis_offchain
Version: 0.5.1
Summary: An overlay for the Walytis blockchain that stores block content off-chain and securely shares it only with trusted peers, using `walytis_identities`.
Author: emendir
Requires-Python: >=3.11
License-File: LICENSE
License-File: LICENSE-CC0
Requires-Dist: walytis_identities>=0.5.0
Dynamic: license-file
